cubescrambler/__init__.py
cubescrambler/bigCubesScrambler.py
cubescrambler/clockScrambler.py
cubescrambler/cuboidsScrambler.py
cubescrambler/megaminxScrambler.py
cubescrambler/pyraminxScrambler.py
cubescrambler/scrambler222.py
cubescrambler/scrambler333.py
cubescrambler/scrambler444.py
cubescrambler/scrambler555.py
cubescrambler/scrambler666.py
cubescrambler/scrambler777.py
cubescrambler/skewbScrambler.py
cubescrambler/squareOneScrambler.py
cubescrambler/js_resources/1x3x3.js
cubescrambler/js_resources/2x2x2.js
cubescrambler/js_resources/2x2x3.js
cubescrambler/js_resources/cross.js
cubescrambler/js_resources/mathlib.js
cubescrambler/js_resources/megascramble.js
cubescrambler/js_resources/pyraminx.js
cubescrambler/js_resources/scramble.js
cubescrambler/js_resources/scramble_333_edit.js
cubescrambler/js_resources/scramble_444.js
cubescrambler/js_resources/scramble_sq1.js
cubescrambler/js_resources/skewb.js
cubescrambler/js_resources/utilscramble.js
cubescrambler-1.0.0.dist-info/LICENSE
cubescrambler-1.0.0.dist-info/METADATA
cubescrambler-1.0.0.dist-info/WHEEL
cubescrambler-1.0.0.dist-info/top_level.txt
cubescrambler-1.0.0.dist-info/RECORD
