Metadata-Version: 2.1
Name: cubescrambler
Version: 1.0.0
Summary: A Python utility package for generating scrambles for twisty puzzles without non-python dependency
Author-email: Márton Kónya <konyamarci52@proton.me>
License: Copyright (c) 2018 The Python Packaging Authority
Project-URL: Homepage, https://github.com/koma52/cubescrambler
Keywords: rubik,cube,scramble
Classifier: License :: OSI Approved :: MIT License
Classifier: Programming Language :: Python
Classifier: Programming Language :: Python :: 3
License-File: LICENSE
